pysweep/__init__.py
pysweep/data_plot.py
pysweep/measurement.py
pysweep/parameter_alias.py
pysweep/sweep_object.py
pysweep/utils.py
pysweep/data_storage/__init__.py
pysweep/data_storage/base_storage.py
pysweep/data_storage/json.py
pysweep/data_storage/pandas_storage.py
pysweep/data_storage/qcodes.py
pysweep/data_storage/spyview.py
pysweep/data_storage/webui_writer.py
pysweep/data_storage/tests/__init__.py
pysweep/data_storage/tests/json.py
pysweep/data_storage/tests/np_storage.py
pysweep/data_storage/tests/spyview.py
pysweep/data_storage/tests/test_webui_writer.py
pysweep/tests/__init__.py
pysweep/tests/test_alias.py
pysweep/tests/test_measure.py
pysweep/tests/test_measure_json.py
pysweep/tests/test_measure_spyview.py
pysweep/tests/test_sweep_object.py
pysweep/tests/testing_utilities.py
pysweep2-0.12.dist-info/DESCRIPTION.rst
pysweep2-0.12.dist-info/METADATA
pysweep2-0.12.dist-info/RECORD
pysweep2-0.12.dist-info/WHEEL
pysweep2-0.12.dist-info/metadata.json
pysweep2-0.12.dist-info/top_level.txt
