Metadata-Version: 2.0
Name: pysweep2
Version: 0.12
Summary: Easily sweep QCoDeS parameters
Home-page: https://github.com/sohailc/pysweep2.0
Author: Sohail Chatoor
Author-email: a-sochat@microsoft.com
License: MIT
Platform: UNKNOWN
Requires-Python: >=3
